obsidian_parser/__init__.py
obsidian_parser/multiplication.py
obsidian_parser/obsidianparser.py
obsidian_parser/wikiparser.py
obsidian_parser-0.3.5.dist-info/METADATA
obsidian_parser-0.3.5.dist-info/WHEEL
obsidian_parser-0.3.5.dist-info/top_level.txt
obsidian_parser-0.3.5.dist-info/RECORD
