Metadata-Version: 2.1
Name: obsidian-parser
Version: 0.3.5
Summary: Grabs all the notes from an Obsidian vault and processes them into a Hugo content directory.
Home-page: https://obsidian-parser.readthedocs.io/
Author: Damian Flynn
Author-email: example@email.com
License: MIT
Classifier: Intended Audience :: Developers
Classifier: License :: OSI Approved :: MIT License
Classifier: Programming Language :: Python
Classifier: Programming Language :: Python :: 3
Classifier: Programming Language :: Python :: 3.6
Classifier: Programming Language :: Python :: 3.7
Classifier: Programming Language :: Python :: 3.8
Classifier: Programming Language :: Python :: 3.9
Classifier: Operating System :: OS Independent
Requires-Dist: numpy
Requires-Dist: python-frontmatter
